vizdataquality/__init__.py
vizdataquality/calculate.py
vizdataquality/datasets.py
vizdataquality/explanation_graph.py
vizdataquality/missing_data_functions.py
vizdataquality/missing_data_io.py
vizdataquality/missing_data_plots.py
vizdataquality/missing_data_utils.py
vizdataquality/plot.py
vizdataquality/report.py
vizdataquality/utils.py
vizdataquality-1.1.3.dist-info/METADATA
vizdataquality-1.1.3.dist-info/WHEEL
vizdataquality-1.1.3.dist-info/licenses/LICENSE
vizdataquality-1.1.3.dist-info/RECORD
