Metadata-Version: 2.4
Name: vizdataquality
Version: 1.1.3
Summary: Visualize data quality
License: Apache-2.0
License-File: LICENSE
Author: Roy Ruddle
Author-email: R.A.Ruddle@leeds.ac.uk
Requires-Python: >=3.9,<=3.13.7
Classifier: Framework :: Jupyter
Classifier: Intended Audience :: Science/Research
Classifier: License :: OSI Approved :: Apache Software License
Classifier: Programming Language :: Python :: 3
Classifier: Programming Language :: Python :: 3.9
Classifier: Programming Language :: Python :: 3.10
Classifier: Programming Language :: Python :: 3.11
Classifier: Programming Language :: Python :: 3.12
Classifier: Programming Language :: Python :: 3.13
Classifier: Topic :: Scientific/Engineering :: Information Analysis
Classifier: Topic :: Scientific/Engineering :: Visualization
Provides-Extra: all
Provides-Extra: doc
Provides-Extra: notebooks
Provides-Extra: test
Requires-Dist: Sphinx (>=7.0,<8.0) ; extra == "doc" or extra == "all"
Requires-Dist: chardet (>=5.2.0,<6.0.0)
Requires-Dist: matplotlib (>=3.7.2,<=3.10) ; extra == "notebooks" or extra == "doc" or extra == "all"
Requires-Dist: myst-parser ; extra == "doc" or extra == "all"
Requires-Dist: notebook (>=6.4,<7.0) ; extra == "notebooks" or extra == "all"
Requires-Dist: numpy (>=1.24,<=2.3.3)
Requires-Dist: pandas (>=2.0,<=2.3.3)
Requires-Dist: pydata-sphinx-theme (>=0.14,<0.15) ; extra == "doc" or extra == "all"
Requires-Dist: pytest (>=6.2,<7.0) ; extra == "test" or extra == "all"
Requires-Dist: tomli (>=2.0,<3.0)
Project-URL: Documentation, https://vizdataquality.readthedocs.io/en/latest/
Project-URL: Repository, https://github.com/royruddle/vizdataquality
